ipyannotator/__init__.py
ipyannotator/_nbdev.py
ipyannotator/annotator.py
ipyannotator/base.py
ipyannotator/bbox_annotator.py
ipyannotator/bbox_canvas.py
ipyannotator/bbox_video_annotator.py
ipyannotator/capture_annotator.py
ipyannotator/custom_input/__init__.py
ipyannotator/custom_input/buttons.py
ipyannotator/custom_input/coordinates.py
ipyannotator/custom_widgets/__init__.py
ipyannotator/custom_widgets/grid_menu.py
ipyannotator/datasets/__init__.py
ipyannotator/datasets/download.py
ipyannotator/datasets/factory.py
ipyannotator/datasets/factory_legacy.py
ipyannotator/datasets/generators.py
ipyannotator/datasets/generators_legacy.py
ipyannotator/debug_utils.py
ipyannotator/docs/__init__.py
ipyannotator/docs/api.py
ipyannotator/docs/input_output.py
ipyannotator/docs/utils.py
ipyannotator/explore_annotator.py
ipyannotator/helpers.py
ipyannotator/im2im_annotator.py
ipyannotator/ipytyping/__init__.py
ipyannotator/ipytyping/annotations.py
ipyannotator/mltypes.py
ipyannotator/navi_widget.py
ipyannotator/right_menu_widget.py
ipyannotator/services/__init__.py
ipyannotator/services/bbox_trajectory.py
ipyannotator/storage.py
ipyannotator-0.8.5.dist-info/LICENSE
ipyannotator-0.8.5.dist-info/WHEEL
ipyannotator-0.8.5.dist-info/METADATA
ipyannotator-0.8.5.dist-info/RECORD
