Metadata-Version: 2.1
Name: ipyannotator
Version: 0.8.5
Summary: The infinitely hackable annotation framework
Home-page: https://github.com/palaimon/ipyannotator
License: Apache-2.0
Author: palaimon.io
Author-email: oss@mail.palaimon.io
Requires-Python: >=3.8
Classifier: License :: OSI Approved :: Apache Software License
Classifier: Programming Language :: Python :: 3
Classifier: Programming Language :: Python :: 3.10
Classifier: Programming Language :: Python :: 3.8
Classifier: Programming Language :: Python :: 3.9
Requires-Dist: PyPubSub (>=4.0.0,<4.1.0)
Requires-Dist: ipycanvas (>=0.10.2)
Requires-Dist: ipyevents (>=0.8.0)
Requires-Dist: ipykernel (>=5.3.4)
Requires-Dist: ipython (>=8.0.1)
Requires-Dist: ipywidgets (>=7.6.0)
Requires-Dist: matplotlib (>=3.4.3)
Requires-Dist: pandas (>=1.2.0)
Requires-Dist: pooch (>=1.5.0,<1.6.0)
Requires-Dist: pydantic (>=1.8.0,<1.9.0)
Requires-Dist: scikit-image (>=0.19.3)
Requires-Dist: tqdm (>=4.64)
Requires-Dist: traitlets (>=5.1.1)
Requires-Dist: voila (>=0.3.1)
Project-URL: Repository, https://github.com/palaimon/ipyannotator
